{"card_name": "William's Epiphany", "color": "R", "rarity": "rare", "type": "Instant", "number": 150, "color_identity": "R", "cost": "{X}{R}{R}", "rules_text": "Exile the top X cards of your library. Until the end of your next turn, you may play those cards.\nEscape\u2013{3}{R}, Exile X other cards from your graveyard. [i](You may cast this card from your graveyard for its escape cost.)[/i]", "pt": "", "special_text": "", "shape": "normal", "set": "HOD", "loyalty": "", "notes": "Escape X Cycle"}