{"card_name": "Ready Response", "color": "G", "rarity": "common", "type": "Enchantment \u2013 Aura", "number": 175, "color_identity": "G", "cost": "{2}{G}", "rules_text": "Enchant creature\nWhen Ready Response enters the battlefield, surveil 2. [i](Look at the top two cards of your library, then put any number of them into your graveyard and the rest on top of your library in any order.)[/i]\nEnchanted creature gets +3/+2 and has vigilance.", "pt": "", "special_text": "", "shape": "normal", "set": "HOD", "loyalty": "", "notes": ""}