{"card_name": "Golna, the First Shah", "color": "G", "rarity": "rare", "type": "Legendary Creature \u2013 Human Noble", "number": 129, "color_identity": "G", "cost": "{2}{G}", "rules_text": "When Golna, the First Shah enters, create Shir, a legendary 3/3 white Cat creature token with trample.\nMonument {5}{G}{G} [i](You may cast this transformed from your graveyard for its monument cost. Exile it if it would leave the battlefield or not resolve.)[/i]", "pt": "1/1", "special_text": "", "shape": "transform double faced", "set": "ALK", "loyalty": "", "card_name2": "The Path of Greatness", "color2": "G", "type2": "Legendary Artifact \u2013 Monument", "cost2": "", "rules_text2": "Creatures you control have trample, haste, and hexproof.\n{2}{G}{G}: Create a 2/2 white Cat creature token.", "pt2": "", "special_text2": "", "loyalty2": "", "notes": ""}