{"card_name": "Secluded Gorgon", "color": "B", "rarity": "common", "type": "Creature \u2013 Gorgon Cleric", "number": 117, "color_identity": "B", "cost": "{1}{B}", "rules_text": "Lifelink\nWhenever Secluded Gorgon dies, you may bless target creature. [i](Create a token copy of this creature\u2019s blessing attached to that permanent.)[/i]", "pt": "2/1", "special_text": "", "shape": "modal double faced", "set": "TRX", "loyalty": "", "card_name2": "Glare of the Gorgon", "color2": "B", "type2": "Enchantment \u2013 Aura Blessing", "cost2": "{1}{B}", "rules_text2": "[i](You may also cast this side from your hand.)[/i]\nFlash\nEnchant creature\nEnchanted creature gets +0/+2 and has deathtouch.", "pt2": "", "special_text2": "", "loyalty2": "", "notes": ""}