{"card_name": "Spikemane Lion", "color": "RG", "rarity": "rare", "type": "Creature \u2013 Cat", "number": 221, "color_identity": "RG", "cost": "{R}{G}", "rules_text": "Whenever Spikemane Lion dies, you may bless target creature. [i](Create a token copy of this creature\u2019s blessing attached to that permanent.)[/i]", "pt": "3/3", "special_text": "", "shape": "modal double faced", "set": "TRX", "loyalty": "", "card_name2": "Spikemane Cloak", "color2": "RG", "type2": "Enchantment \u2013 Aura Blessing", "cost2": "{R}{G}", "rules_text2": "[i](You may also cast this side from your hand.)[/i]\nEnchant creature\nWhenever enchanted creature becomes the target of a spell or ability, put a +1/+1 counter on it and that creature deals 1 damage to each opponent. This ability triggers no more than twice each turn.", "pt2": "", "special_text2": "", "loyalty2": "", "notes": "Combat STuff"}