{"card_name": "Reconstruct from Scrap", "color": "B", "rarity": "mythic", "type": "Sorcery", "number": 173, "color_identity": "B", "cost": "{3}{B}", "rules_text": "Exile up to two creature cards from your graveyard. If you do, create a token that\u2019s a copy of one of those cards with a number of additional +1/+1 counters on it equal to the power of the other card.", "pt": "", "special_text": "", "shape": "normal", "set": "ZANG", "loyalty": "", "notes": "Planename: New Phyrexia\nReanimation spell"}