{"card_name": "Acolyte of Water", "color": "U", "rarity": "rare", "type": "Creature \u2013 Nephilim Cleric", "number": 40, "color_identity": "U", "cost": "{2}{U}", "rules_text": "Whenever you draw a card, put a +1/+1 counter on Acolyte of Water.\nSurpass {5}{U} [i]({5}{U}: Transform this creature. This costs {1} less to activate for each counter on it. Activate only as a sorcery.)[/i]", "pt": "2/2", "special_text": "", "shape": "transform double faced", "set": "ROS", "loyalty": "", "card_name2": "Acolyte of Life", "color2": "U", "type2": "Creature \u2013 Angel Cleric", "cost2": "", "rules_text2": "Flying\nWhenever you draw a card, put a +1/+1 counter on Acolyte of Life.\nRemove two counters from Acolyte of Life: It phases out. [i](Treat it and anything attached to it as though they don\u2019t exist until its controller\u2019s next turn.)[/i]", "pt2": "3/3", "special_text2": "", "loyalty2": "", "notes": "fullart\nMartoob"}