{"card_name": "Leading Clergy", "color": "W", "rarity": "common", "type": "Creature \u2013 Construct Cleric", "number": 16, "color_identity": "W", "cost": "{2}{W}", "rules_text": "Whenever Leading Clergy attacks, you may pay {W}. If you do, audition for white. [i](Create a 1/1 Construct Actor creature token, a Scout Role giving 2/3 and vigilance, or a Cleric Role giving 2/2 and lifelink. Roles replace older ones.)[/i]", "pt": "1/3", "special_text": "", "shape": "normal", "set": "ACT", "loyalty": "", "notes": ""}