{"card_name": "Crime Spree", "color": "R", "rarity": "rare", "type": "Enchantment", "number": 129, "color_identity": "R", "cost": "{2}{R}{R}", "rules_text": "When Crime Spree enters, create a 1/1 red Human creature token. It gains haste until end of turn. [i](Choose one or more additional costs.)[/i]\nAt the beginning of your upkeep, if you didn\u2019t disturb the peace since the beginning of your last turn, sacrifice Crime Spree. [i](Casting a spell on an opponent\u2019s turn and one or more creatures dealing combat damage to an opponent disturb the peace.)[/i]\nCreatures you control get +2/+0.", "pt": "", "special_text": "", "shape": "normal", "set": "SRC", "loyalty": "", "notes": ""}