[{"card_name": "Hollow Simulacrum", "number": 18, "shape": "normal"}, {"card_name": "Shahmaran of the Empty Sea", "number": 68, "shape": "normal"}, {"card_name": "Acrimony", "number": 79, "shape": "normal"}, {"card_name": "In Blood, Vengeance", "number": 137, "shape": "normal"}, {"card_name": "Colossus of Alkabah", "number": 160, "shape": "normal"}, {"card_name": "Chained to the Roc", "number": 9, "shape": "normal"}, {"card_name": "Acolyte of Water", "number": 40, "shape": "transform double faced"}, {"card_name": "Backalley Connections", "number": 83, "shape": "normal"}, {"card_name": "Archfiend of Rage", "number": 121, "shape": "normal"}, {"card_name": "Danaj Sightseer", "number": 166, "shape": "normal"}, {"card_name": "Consult the Lineage", "number": 11, "shape": "normal"}, {"card_name": "Dawn Over Nizev", "number": 48, "shape": "normal"}, {"card_name": "Dawn Over Kaneh", "number": 89, "shape": "normal"}, {"card_name": "Cyrukans Elite", "number": 125, "shape": "normal"}, {"card_name": "Dawn Over Danaj", "number": 167, "shape": "normal"}, {"card_name": "Dawn Over Soli", "number": 13, "shape": "normal"}, {"card_name": "Empyrean Scholar", "number": 50, "shape": "normal"}, {"card_name": "Desolate Advance", "number": 91, "shape": "normal"}, {"card_name": "Dawn Over Avaz", "number": 126, "shape": "normal"}, {"card_name": "Dreaded of Sahra", "number": 170, "shape": "normal"}, {"card_name": "Harsh Spahbed", "number": 17, "shape": "normal"}, {"card_name": "Ingratiate", "number": 52, "shape": "normal"}, {"card_name": "Jahi of Endless Hunger", "number": 100, "shape": "normal"}, {"card_name": "Furious Blow", "number": 133, "shape": "normal"}, {"card_name": "Herald of Ruination", "number": 178, "shape": "transform double faced"}, {"card_name": "Listless Maneli", "number": 24, "shape": "transform double faced"}, {"card_name": "Martoob Lifeshaper", "number": 54, "shape": "normal"}, {"card_name": "Mehr's Unending Horde", "number": 104, "shape": "normal"}, {"card_name": "Huma of Glory", "number": 135, "shape": "normal"}, {"card_name": "Inspiring Tactician", "number": 179, "shape": "normal"}, {"card_name": "Rhythm of Soli", "number": 28, "shape": "normal"}, {"card_name": "Peer into Eternity", "number": 58, "shape": "normal"}, {"card_name": "Reckoner of Kaneh", "number": 108, "shape": "normal"}, {"card_name": "Jals Spawn", "number": 139, "shape": "normal"}, {"card_name": "Rally the Armies", "number": 186, "shape": "normal"}, {"card_name": "Savior Tactician", "number": 29, "shape": "normal"}, {"card_name": "Rhythm of Nizev", "number": 63, "shape": "normal"}, {"card_name": "Rhythm of Kaneh", "number": 110, "shape": "normal"}, {"card_name": "Last Priest of Hadak", "number": 141, "shape": "normal"}, {"card_name": "Rhythm of Danaj", "number": 187, "shape": "normal"}, {"card_name": "Solis Crossbowmaster", "number": 33, "shape": "normal"}, {"card_name": "Scorned Arcanist", "number": 66, "shape": "normal"}, {"card_name": "Triumphant Greed", "number": 116, "shape": "normal"}, {"card_name": "Rhythm of Avaz", "number": 150, "shape": "normal"}, {"card_name": "Spawn of Andazir", "number": 193, "shape": "normal"}, {"card_name": "Wretched Skulker", "number": 37, "shape": "normal"}, {"card_name": "Streetwise Spellseeker", "number": 71, "shape": "normal"}, {"card_name": "Vagabond of the Dunes", "number": 117, "shape": "transform double faced"}, {"card_name": "Slinking Raider", "number": 153, "shape": "transform double faced"}, {"card_name": "Variety of Goods", "number": 195, "shape": "normal"}, {"card_name": "Advocate of Ideals", "number": 1, "shape": "normal"}, {"card_name": "Angel of Wisdom", "number": 43, "shape": "normal"}, {"card_name": "Andazirs Disdain", "number": 80, "shape": "normal"}, {"card_name": "Advocate of Foibles", "number": 118, "shape": "normal"}, {"card_name": "Accept into the Fold", "number": 157, "shape": "normal"}, {"card_name": "Avaz Rising", "number": 3, "shape": "normal"}, {"card_name": "Consult the Cosmos", "number": 46, "shape": "normal"}, {"card_name": "Blackfeather Cleric", "number": 84, "shape": "transform double faced"}, {"card_name": "Ambitious Truthseeker", "number": 119, "shape": "normal"}, {"card_name": "Convicted Strike", "number": 162, "shape": "normal"}, {"card_name": "Blessing from Wings on High", "number": 6, "shape": "normal"}, {"card_name": "Crisis in Danaj", "number": 47, "shape": "normal"}, {"card_name": "Chaosbender", "number": 86, "shape": "normal"}, {"card_name": "Crisis in Nizev", "number": 124, "shape": "normal"}, {"card_name": "Crisis in Avaz", "number": 163, "shape": "normal"}, {"card_name": "Confine to the Oasis", "number": 10, "shape": "normal"}, {"card_name": "Martoob's Forerunner", "number": 55, "shape": "normal"}, {"card_name": "Crisis in Kaneh", "number": 87, "shape": "normal"}, {"card_name": "Djinn of the Twisted Wish", "number": 127, "shape": "normal"}, {"card_name": "Dunesea Ranger", "number": 171, "shape": "normal"}, {"card_name": "Crisis in Soli", "number": 12, "shape": "normal"}, {"card_name": "Nephilim Wisdomancer", "number": 56, "shape": "normal"}, {"card_name": "Danaj Rising", "number": 88, "shape": "normal"}, {"card_name": "Firebolt", "number": 131, "shape": "normal"}, {"card_name": "Fracturing Swipe", "number": 175, "shape": "normal"}, {"card_name": "Dunesea Merchant", "number": 14, "shape": "normal"}, {"card_name": "Nizev Rising", "number": 57, "shape": "normal"}, {"card_name": "Dutybound Ghul", "number": 93, "shape": "normal"}, {"card_name": "Kaneh Rising", "number": 140, "shape": "normal"}, {"card_name": "Gather the Forces", "number": 176, "shape": "normal"}, {"card_name": "Fury of Cyrukan", "number": 15, "shape": "normal"}, {"card_name": "Petty Thief", "number": 59, "shape": "transform double faced"}, {"card_name": "Fulfill the Contract", "number": 99, "shape": "normal"}, {"card_name": "Manifold Manipulator", "number": 142, "shape": "normal"}, {"card_name": "Heartweaver", "number": 177, "shape": "normal"}, {"card_name": "Garrison Warden", "number": 16, "shape": "transform double faced"}, {"card_name": "Prepare for War", "number": 60, "shape": "normal"}, {"card_name": "Kingpin of Nizev", "number": 102, "shape": "normal"}, {"card_name": "Paygan Firebinder", "number": 143, "shape": "normal"}, {"card_name": "Quake Devourer", "number": 184, "shape": "normal"}, {"card_name": "Hooded Mystic", "number": 19, "shape": "normal"}, {"card_name": "Scholar's Delight", "number": 64, "shape": "normal"}, {"card_name": "Oracle of the Unseen", "number": 105, "shape": "normal"}, {"card_name": "The Pillaging of Kaneh", "number": 145, "shape": "normal"}, {"card_name": "Quickstep Ranger", "number": 185, "shape": "transform double faced"}, {"card_name": "Settling of Kaneh", "number": 31, "shape": "normal"}, {"card_name": "Settling of Soli", "number": 67, "shape": "normal"}, {"card_name": "Settling of Nizev", "number": 113, "shape": "normal"}, {"card_name": "Rahstahde Swiftspear", "number": 146, "shape": "transform double faced"}, {"card_name": "Settling of Danaj", "number": 189, "shape": "normal"}, {"card_name": "Standoff", "number": 34, "shape": "normal"}, {"card_name": "Tidebender", "number": 73, "shape": "normal"}, {"card_name": "Smiting Helix", "number": 114, "shape": "normal"}, {"card_name": "Refracting Image", "number": 148, "shape": "normal"}, {"card_name": "Shah's Caravan", "number": 190, "shape": "normal"}, {"card_name": "Zagos Roc", "number": 38, "shape": "normal"}, {"card_name": "Wade Through Treasures", "number": 76, "shape": "normal"}, {"card_name": "Traverse the Endless Well", "number": 115, "shape": "normal"}, {"card_name": "Settling of Avaz", "number": 151, "shape": "normal"}, {"card_name": "Soli Rising", "number": 192, "shape": "normal"}, {"card_name": "Assault on Soli", "number": 2, "shape": "normal"}, {"card_name": "Acquiesce Position", "number": 41, "shape": "normal"}, {"card_name": "Andazirs Pact", "number": 81, "shape": "normal"}, {"card_name": "Andazir Veteran", "number": 120, "shape": "normal"}, {"card_name": "Avaz Sentry", "number": 158, "shape": "transform double faced"}, {"card_name": "Banishment of Aspirations", "number": 4, "shape": "normal"}, {"card_name": "Adrift Surveyor", "number": 42, "shape": "transform double faced"}, {"card_name": "Astral Assassination", "number": 82, "shape": "normal"}, {"card_name": "Bloodcloaked Wrecker", "number": 122, "shape": "normal"}, {"card_name": "Cherish the Past", "number": 159, "shape": "normal"}, {"card_name": "Birthright Proselyte", "number": 5, "shape": "normal"}, {"card_name": "Benevolent Host", "number": 44, "shape": "normal"}, {"card_name": "Castaway's Remorse", "number": 85, "shape": "normal"}, {"card_name": "Conjure Quicksand", "number": 123, "shape": "normal"}, {"card_name": "Commanders Guidance", "number": 161, "shape": "normal"}, {"card_name": "Blessing of Respite", "number": 7, "shape": "normal"}, {"card_name": "Brightwing Sphinx", "number": 45, "shape": "normal"}, {"card_name": "Demon of Endless Hunger", "number": 90, "shape": "normal"}, {"card_name": "Evening Serenade", "number": 128, "shape": "normal"}, {"card_name": "Crush Opposition", "number": 164, "shape": "normal"}, {"card_name": "Cast Judgment", "number": 8, "shape": "normal"}, {"card_name": "Dewdrop Ordainer", "number": 49, "shape": "normal"}, {"card_name": "Drag Through the Alley", "number": 92, "shape": "normal"}, {"card_name": "Eyes of Cyrukan", "number": 129, "shape": "normal"}, {"card_name": "Cultivator of Crops", "number": 165, "shape": "normal"}, {"card_name": "In Defense of Soli", "number": 20, "shape": "normal"}, {"card_name": "Implacable Djinn", "number": 51, "shape": "normal"}, {"card_name": "Enigmatic Herald", "number": 94, "shape": "normal"}, {"card_name": "Figments of Warriors Lost", "number": 130, "shape": "normal"}, {"card_name": "Day at the Market", "number": 168, "shape": "normal"}, {"card_name": "Inspirational Beacon", "number": 21, "shape": "normal"}, {"card_name": "Maneli Ambassador", "number": 53, "shape": "normal"}, {"card_name": "Esoteric Visionary", "number": 95, "shape": "normal"}, {"card_name": "Frantic Efreetspeaker", "number": 132, "shape": "normal"}, {"card_name": "Div of Lethargic Ideals", "number": 169, "shape": "normal"}, {"card_name": "Kaneh Scribe", "number": 22, "shape": "normal"}, {"card_name": "Regretful Chronicler", "number": 61, "shape": "transform double faced"}, {"card_name": "EverWandering Vagabond", "number": 96, "shape": "transform double faced"}, {"card_name": "Hesitant Vanguard", "number": 134, "shape": "transform double faced"}, {"card_name": "Erode", "number": 172, "shape": "normal"}, {"card_name": "Keen Blademaster", "number": 23, "shape": "normal"}, {"card_name": "Reject Wickedness", "number": 62, "shape": "normal"}, {"card_name": "Fatal Strike", "number": 97, "shape": "normal"}, {"card_name": "Ignite the Inner Flame", "number": 136, "shape": "normal"}, {"card_name": "Expose Wickedness", "number": 173, "shape": "normal"}, {"card_name": "Lowly Cataphract", "number": 25, "shape": "transform double faced"}, {"card_name": "Scope the Cosmos", "number": 65, "shape": "normal"}, {"card_name": "Fiendish Bruiser", "number": 98, "shape": "normal"}, {"card_name": "Incendiary Flow", "number": 138, "shape": "normal"}, {"card_name": "Fell LanternBearer", "number": 174, "shape": "normal"}, {"card_name": "Mahara Enforcer", "number": 26, "shape": "normal"}, {"card_name": "Sinking Pessimism", "number": 69, "shape": "normal"}, {"card_name": "Kaneh Siege", "number": 101, "shape": "normal"}, {"card_name": "Piercing Arrow", "number": 144, "shape": "normal"}, {"card_name": "Ironclad Sentry", "number": 180, "shape": "normal"}, {"card_name": "Prepare for Rest", "number": 27, "shape": "normal"}, {"card_name": "Skyborne Strategist", "number": 70, "shape": "normal"}, {"card_name": "Manipulations of the Div", "number": 103, "shape": "normal"}, {"card_name": "Refitting for Battle", "number": 147, "shape": "normal"}, {"card_name": "Kahroba Patrol", "number": 181, "shape": "normal"}, {"card_name": "Sentinel of Avaz", "number": 30, "shape": "normal"}, {"card_name": "Tempt with Gifts", "number": 72, "shape": "normal"}, {"card_name": "Poison-Sky Acolyte", "number": 106, "shape": "normal"}, {"card_name": "Regroup and Stockpile", "number": 149, "shape": "normal"}, {"card_name": "Martoob Hawker", "number": 182, "shape": "normal"}, {"card_name": "Show of Unwavering Honor", "number": 32, "shape": "normal"}, {"card_name": "Tiller of the Paltry Lie", "number": 74, "shape": "normal"}, {"card_name": "Prepare for Assault", "number": 107, "shape": "normal"}, {"card_name": "Shipment Overseer", "number": 152, "shape": "transform double faced"}, {"card_name": "Nimble Pathfinder", "number": 183, "shape": "transform double faced"}, {"card_name": "Unyielding Aswaran", "number": 35, "shape": "normal"}, {"card_name": "Truthseeker Prodigy", "number": 75, "shape": "normal"}, {"card_name": "Refine to Nothing", "number": 109, "shape": "normal"}, {"card_name": "Tomb-Raider Duo", "number": 154, "shape": "normal"}, {"card_name": "Settling Alkabah", "number": 188, "shape": "normal"}, {"card_name": "Vanguard of Glory", "number": 36, "shape": "normal"}, {"card_name": "Wave Shield", "number": 77, "shape": "normal"}, {"card_name": "Ruthless Advisor", "number": 111, "shape": "transform double faced"}, {"card_name": "Truthbearing Peri", "number": 155, "shape": "normal"}, {"card_name": "Shah's Proclamation", "number": 191, "shape": "normal"}, {"card_name": "Zealot of Mahara", "number": 39, "shape": "transform double faced"}, {"card_name": "Wisdom of the Dunesea", "number": 78, "shape": "normal"}, {"card_name": "Selfserving Ghul", "number": 112, "shape": "normal"}, {"card_name": "Vicious Shamshir", "number": 156, "shape": "normal"}, {"card_name": "Unstoppable Zealot", "number": 194, "shape": "normal"}, {"card_name": "er"}, {"card_name": "er"}, {"card_name": "er"}, {"card_name": "er"}, {"card_name": "er"}, {"card_name": "Atieh, Seer of Distant Futures", "number": 196, "shape": "class"}, {"card_name": "Fahrib the EverScheming", "number": 199, "shape": "class"}, {"card_name": "Andazir, First to Aspire", "number": 202, "shape": "class"}, {"card_name": "Sahra, Hadak's Last Warrior", "number": 207, "shape": "class"}, {"card_name": "Abwad Kahroba, Failed Son", "number": 208, "shape": "class"}, {"card_name": "Atiehs Disciple", "number": 197, "shape": "transform double faced"}, {"card_name": "Persecutor of Truths", "number": 200, "shape": "normal"}, {"card_name": "Bloodthirsty Manticore", "number": 203, "shape": "transform double faced"}, {"card_name": "Herald of Untold Riches", "number": 206, "shape": "normal"}, {"card_name": "A Matricide Most Foul", "number": 209, "shape": "normal"}, {"card_name": "Herald of Atieh", "number": 198, "shape": "normal"}, {"card_name": "Ruthless Bakhtak", "number": 201, "shape": "normal"}, {"card_name": "Djinn of the Waning Candle", "number": 204, "shape": "normal"}, {"card_name": "Guardians of Kallians Tomb", "number": 205, "shape": "normal"}, {"card_name": "Valiant Cataphract", "number": 210, "shape": "normal"}, {"card_name": "Augur of Pathways", "number": 259, "shape": "normal"}, {"card_name": "Cunning Plan", "number": 260, "shape": "normal"}, {"card_name": "Offering to the Div", "number": 261, "shape": "normal"}, {"card_name": "Bazaar Braggart", "number": 262, "shape": "normal"}, {"card_name": "Marshal of Brethren", "number": 263, "shape": "normal"}, {"card_name": "er"}, {"card_name": "er"}, {"card_name": "er"}, {"card_name": "er"}, {"card_name": "er"}, {"card_name": "Mahara, General of All", "number": 212, "shape": "class"}, {"card_name": "Tamaak the Arid Swarm", "number": 219, "shape": "class"}, {"card_name": "Martoob of Flowing Life", "number": 224, "shape": "class"}, {"card_name": "Rahstahde, Brand of Truth", "number": 215, "shape": "class"}, {"card_name": "Cyrukan of Heart and Iron", "number": 220, "shape": "class"}, {"card_name": "Mehr's Last Captain", "number": 213, "shape": "normal"}, {"card_name": "Hayat, Hungering Bakhtak", "number": 266, "shape": "transform double faced"}, {"card_name": "Nozar, Dunesea Merchant", "number": 225, "shape": "normal"}, {"card_name": "Abbas and Laila", "number": 214, "shape": "normal"}, {"card_name": "The Lost and Seeking", "number": 269, "shape": "transform double faced"}, {"card_name": "Angel of Despair", "number": 211, "shape": "normal"}, {"card_name": "Azra Warshaper", "number": 217, "shape": "normal"}, {"card_name": "Coagulating Strength", "number": 223, "shape": "normal"}, {"card_name": "Selection at Danaj", "number": 216, "shape": "normal"}, {"card_name": "Figments of the Muktann", "number": 221, "shape": "normal"}, {"card_name": "Toil Beyond Death", "number": 264, "shape": "normal"}, {"card_name": "Herald of Tamaak", "number": 218, "shape": "normal"}, {"card_name": "Venerable Skyblade", "number": 270, "shape": "normal"}, {"card_name": "Rahstahde Pledge", "number": 265, "shape": "normal"}, {"card_name": "Zagos Abomination", "number": 222, "shape": "normal"}, {"card_name": "e"}, {"card_name": "Openmaw Demon", "number": 267, "shape": "normal"}, {"card_name": "e"}, {"card_name": "e"}, {"card_name": "Battlefield Tiger", "number": 268, "shape": "normal"}, {"card_name": "er"}, {"card_name": "er"}, {"card_name": "er"}, {"card_name": "er"}, {"card_name": "er"}, {"card_name": "Parastu, Soli's Overseer", "number": 248, "shape": "normal"}, {"card_name": "Div of Unsettling Secrets", "number": 237, "shape": "normal"}, {"card_name": "Sadegh, Tyrant of Nizev", "number": 251, "shape": "normal"}, {"card_name": "Predatory Tombstalker", "number": 250, "shape": "normal"}, {"card_name": "Shideh, Avazs Conqueror", "number": 253, "shape": "normal"}, {"card_name": "Adrift into Endless Stories", "number": 227, "shape": "normal"}, {"card_name": "Acolyte of the Far Winds", "number": 226, "shape": "normal"}, {"card_name": "Echo of the Simurgh", "number": 241, "shape": "normal"}, {"card_name": "Aswaran Conquerer", "number": 229, "shape": "normal"}, {"card_name": "Dunesea Dreadstalker", "number": 240, "shape": "normal"}, {"card_name": "er"}, {"card_name": "er"}, {"card_name": "er"}, {"card_name": "er"}, {"card_name": "er"}, {"card_name": "Zhubin, Spear of Kaneh", "number": 258, "shape": "normal"}, {"card_name": "Ineptitude", "number": 244, "shape": "normal"}, {"card_name": "The Brink of War", "number": 231, "shape": "normal"}, {"card_name": "From the Skies, Peace", "number": 243, "shape": "normal"}, {"card_name": "Dali, the Eyes of Danaj", "number": 234, "shape": "normal"}, {"card_name": "On Andazirs Whims", "number": 247, "shape": "normal"}, {"card_name": "Spawn of Hadak", "number": 254, "shape": "normal"}, {"card_name": "Div's Onslaught", "number": 238, "shape": "normal"}, {"card_name": "Djinn of Unfolding Truths", "number": 239, "shape": "normal"}, {"card_name": "Descent of the Div", "number": 235, "shape": "normal"}, {"card_name": "er"}, {"card_name": "er"}, {"card_name": "er"}, {"card_name": "er"}, {"card_name": "er"}, {"card_name": "Pariahs Bargain", "number": 249, "shape": "normal"}, {"card_name": "Zareen Kahroba, Shah", "number": 257, "shape": "normal"}, {"card_name": "Andazir's Command", "number": 228, "shape": "normal"}, {"card_name": "Atieh's Command", "number": 230, "shape": "normal"}, {"card_name": "Cosmic Banishment", "number": 232, "shape": "normal"}, {"card_name": "Cyrukans Command", "number": 233, "shape": "normal"}, {"card_name": "Disappointment", "number": 236, "shape": "normal"}, {"card_name": "Fahribs Command", "number": 242, "shape": "normal"}, {"card_name": "Iridescent Savior", "number": 245, "shape": "normal"}, {"card_name": "Obstinate Wishgranter", "number": 246, "shape": "normal"}, {"card_name": "Sahras Harbinger", "number": 252, "shape": "normal"}, {"card_name": "Swooping Manticore", "number": 255, "shape": "normal"}, {"card_name": "Tamaaks Command", "number": 256, "shape": "normal"}, {"card_name": "e"}, {"card_name": "e"}, {"card_name": "er"}, {"card_name": "er"}, {"card_name": "er"}, {"card_name": "er"}, {"card_name": "er"}, {"card_name": "Feather of the Simurgh", "number": 273, "shape": "normal"}, {"card_name": "Attendant of Graves", "number": 271, "shape": "normal"}, {"card_name": "Banner of Warfare", "number": 272, "shape": "normal"}, {"card_name": "Wayfinder's Bauble", "number": 274, "shape": "normal"}, {"card_name": "e"}, {"card_name": "er"}, {"card_name": "er"}, {"card_name": "er"}, {"card_name": "er"}, {"card_name": "er"}, {"card_name": "Soli Fortress", "number": 288, "shape": "normal"}, {"card_name": "Nizev Fortress", "number": 285, "shape": "normal"}, {"card_name": "Kaneh Fortress", "number": 282, "shape": "normal"}, {"card_name": "Avaz Fortress", "number": 275, "shape": "normal"}, {"card_name": "Danaj Fortress", "number": 279, "shape": "normal"}, {"card_name": "er"}, {"card_name": "er"}, {"card_name": "er"}, {"card_name": "er"}, {"card_name": "er"}, {"card_name": "Soli Sanctuary", "number": 289, "shape": "normal"}, {"card_name": "Nizev Temple", "number": 287, "shape": "normal"}, {"card_name": "Kaneh Temple", "number": 284, "shape": "normal"}, {"card_name": "Avaz Temple", "number": 277, "shape": "normal"}, {"card_name": "Soli Temple", "number": 290, "shape": "normal"}, {"card_name": "er"}, {"card_name": "er"}, {"card_name": "er"}, {"card_name": "er"}, {"card_name": "er"}, {"card_name": "Kaneh Sanctuary", "number": 283, "shape": "normal"}, {"card_name": "Danaj Temple", "number": 281, "shape": "normal"}, {"card_name": "Danaj Sanctuary", "number": 280, "shape": "normal"}, {"card_name": "Nizev Sanctuary", "number": 286, "shape": "normal"}, {"card_name": "Avaz Sanctuary", "number": 276, "shape": "normal"}, {"card_name": "er"}, {"card_name": "er"}, {"card_name": "er"}, {"card_name": "er"}, {"card_name": "er"}, {"card_name": "er"}, {"card_name": "er"}, {"card_name": "er"}, {"card_name": "er"}, {"card_name": "er"}, {"card_name": "Burgeoning Satrapy", "number": 278, "shape": "normal"}, {"card_name": "e"}, {"card_name": "e"}, {"card_name": "e"}, {"card_name": "e"}, {"card_name": "er"}, {"card_name": "er"}, {"card_name": "er"}, {"card_name": "er"}, {"card_name": "er"}, {"card_name": "Angel Soldier", "number": 1, "shape": "token"}, {"card_name": "Soldier", "number": 2, "shape": "token"}, {"card_name": "Horror", "number": 3, "shape": "token"}, {"card_name": "Insect", "number": 4, "shape": "token"}, {"card_name": "Snake", "number": 5, "shape": "token"}, {"card_name": "Soldier Army", "number": 6, "shape": "token"}, {"card_name": "Cleric", "number": 7, "shape": "token"}, {"card_name": "Treasure", "number": 8, "shape": "token"}, {"card_name": "e"}, {"card_name": "e"}]