{"card_name": "Nahiri's Resolve", "color": "WR", "rarity": "mythic", "type": "Enchantment", "number": 245, "color_identity": "WR", "cost": "{3}{R}{W}", "rules_text": "Creatures you control get +1/+0 and have haste.\nAt the beginning of your end step, exile any number of nontoken artifacts and/or creatures you control. Return those cards to the battlefield under their owner\u2019s control at the beginning of your next upkeep.", "pt": "", "special_text": "", "shape": "normal", "set": "ZNU", "loyalty": "", "notes": "Story Spotlight 9\nTOTALLYCOMPLETED"}