{"card_name": "Inundate in Bureaucracy", "color": "WU", "rarity": "rare", "type": "Enchantment", "number": 161, "color_identity": "WU", "cost": "{1}{W}{U}", "rules_text": "When Inundate in Bureaucracy enters the battlefield or whenever an opponent casts their second spell each turn, put a filibuster counter on Inundate in Bureaucracy.\nCreatures can\u2019t attack you or planeswalkers you control unless their controller pays {X} for each creature they control that\u2019s attacking you, where X is the number of filibuster counters on Inundate in Bureaucracy.", "pt": "", "special_text": "", "shape": "normal", "set": "RAR", "loyalty": "", "notes": "Azorius"}