{"card_name": "Wreathed Sentinel", "color": "WG", "rarity": "uncommon", "type": "Enchantment Creature \u2013 Spirit Knight", "number": 95, "color_identity": "WG", "cost": "{4}{G}{W}", "rules_text": "Effigy {G}{W} [i](If you cast this for its effigy cost, it isn't a creature until you pay its mana cost as a sorcery.)[/i]\nVigilance\nCreature tokens you control get +1/+1 and have vigilance.", "flavor_text": "[i][/i]", "pt": "6/6", "special_text": "", "shape": "normal", "set": "ATR", "loyalty": "", "artist": "Luca Finotto", "notes": "", "image_type": "png"}